interact_ms/__init__.py
interact_ms/api.py
interact_ms/clean_up.py
interact_ms/constants.py
interact_ms/execute.py
interact_ms/handle_results.py
interact_ms/html_snippets.py
interact_ms/inspire_script.py
interact_ms/queue_manager.py
interact_ms/utils.py
interact_ms/static/aboutus.jpeg
interact_ms/static/favicon.ico
interact_ms/static/help.png
interact_ms/static/inSPIRE-logo-nobg.png
interact_ms/static/inSPIRE-logo.png
interact_ms/static/index.js
interact_ms/static/interact-ms-homepage.png
interact_ms/static/qsb-logo.png
interact_ms/static/styles/style.css
interact_ms/templates/404.html
interact_ms/templates/about.html
interact_ms/templates/contact.html
interact_ms/templates/delete.html
interact_ms/templates/download.html
interact_ms/templates/failed.html
interact_ms/templates/faq.html
interact_ms/templates/home.html
interact_ms/templates/index.html
interact_ms/templates/ms.html
interact_ms/templates/parameters.html
interact_ms/templates/proteome-pathogen.html
interact_ms/templates/proteome-standard.html
interact_ms/templates/queued.html
interact_ms/templates/ready.html
interact_ms/templates/references.html
interact_ms/templates/search.html
interact_ms/templates/subset.html
interact_ms/templates/usecase.html
interact_ms/templates/view-queue.html
interact_ms/templates/waiting.html
interact_ms-1.0.dist-info/licenses/LICENSE
interact_ms-1.0.dist-info/METADATA
interact_ms-1.0.dist-info/WHEEL
interact_ms-1.0.dist-info/entry_points.txt
interact_ms-1.0.dist-info/top_level.txt
interact_ms-1.0.dist-info/RECORD
