Metadata-Version: 2.4
Name: interact-ms
Version: 1.0
Summary: Interactive GUI for mass spectrometry identification and analysis.
Author: John Cormican, Sahil Khan, Juliane Liepe, Manuel S. Pereira
Author-email: juliane.liepe@mpinat.mpg.de
Project-URL: Homepage, https://github.com/QuantSysBio/interact-ms
Project-URL: Tracker, https://github.com/QuantSysBio/interact-ms/issues
Requires-Python: >=3.11
License-File: LICENSE
Requires-Dist: inspirems==2.0
Requires-Dist: blinker==1.6.2
Requires-Dist: click==8.1.3
Requires-Dist: flask==2.3.2
Requires-Dist: flask_cors==3.0.10
Requires-Dist: itsdangerous==2.1.2
Requires-Dist: MarkupSafe==2.1.3
Requires-Dist: psutil==5.9.6
Requires-Dist: Werkzeug==3.0.1
Requires-Dist: six==1.16.0
Dynamic: author
Dynamic: author-email
Dynamic: description
Dynamic: description-content-type
Dynamic: license-file
Dynamic: project-url
Dynamic: requires-dist
Dynamic: requires-python
Dynamic: summary
